dork_recon/__init__.py
dork_recon/default_dorks.json
dork_recon/dork_recon.py
dork_recon-0.1.9.dist-info/LICENSE
dork_recon-0.1.9.dist-info/METADATA
dork_recon-0.1.9.dist-info/WHEEL
dork_recon-0.1.9.dist-info/entry_points.txt
dork_recon-0.1.9.dist-info/RECORD
