Metadata-Version: 2.1
Name: dork-recon
Version: 0.1.9
Summary: Simple recon tool using google dork
Author: Renato Pinheiro
Requires-Python: >=3.11,<4.0
Classifier: Programming Language :: Python :: 3
Classifier: Programming Language :: Python :: 3.11
Classifier: Programming Language :: Python :: 3.12
Requires-Dist: bs4 (>=0.0.2,<0.0.3)
Requires-Dist: requests (>=2.32.3,<3.0.0)
Requires-Dist: requests-tor (>=1.4,<2.0)
Requires-Dist: rich (>=13.8.1,<14.0.0)
